Metadata-Version: 2.1
Name: my-library-mk-005_2
Version: 0.1
Summary: A Python library
Author: Mushaim Khan
Author-email: mushaimk01@gmail.com
